common/__init__.py
common/constants.py
common/handler.py
common/aws/__init__.py
common/aws/core.py
common/aws/secret_manager.py
common/db/__init__.py
common/db/manager.py
common/db/helpers/__init__.py
common/db/helpers/constants.py
common/db/helpers/custom_fields.py
common/db/helpers/date_time_utils.py
common/db/helpers/tables.py
common/db/helpers/utils.py
common/db/migrations/__init__.py
common/db/migrations/migration_0.py
common/db/migrations/runner.py
common/db/migrations/data_migration/__init__.py
common/db/migrations/data_migration/parser.py
common/db/models/__init__.py
common/db/models/base.py
common/db/models/migrations.py
common/db/models/user.py
common_code_knoww-0.0.1.dist-info/METADATA
common_code_knoww-0.0.1.dist-info/WHEEL
common_code_knoww-0.0.1.dist-info/top_level.txt
common_code_knoww-0.0.1.dist-info/RECORD
